ani2xcur/__init__.py
ani2xcur/cmd.py
ani2xcur/config.py
ani2xcur/downloader.py
ani2xcur/logger.py
ani2xcur/smart_finder.py
ani2xcur/updater.py
ani2xcur/utils.py
ani2xcur/version.py
ani2xcur/cli/__init__.py
ani2xcur/cli/cli.py
ani2xcur/cli/convert.py
ani2xcur/cli/cursor.py
ani2xcur/cli/image_magick.py
ani2xcur/cli/main.py
ani2xcur/cli/system.py
ani2xcur/config_parse/__init__.py
ani2xcur/config_parse/linux.py
ani2xcur/config_parse/parse.py
ani2xcur/config_parse/win.py
ani2xcur/cursor_conversion/__init__.py
ani2xcur/cursor_conversion/convert.py
ani2xcur/cursor_conversion/win2xcur_warp.py
ani2xcur/file_operations/__init__.py
ani2xcur/file_operations/archive_manager.py
ani2xcur/file_operations/file_manager.py
ani2xcur/manager/__init__.py
ani2xcur/manager/base.py
ani2xcur/manager/image_magick_manager.py
ani2xcur/manager/linux_cur_manager.py
ani2xcur/manager/regedit.py
ani2xcur/manager/win_cur_manager.py
ani2xcur/manager/win_env_val_manager.py
ani2xcur/manager/desktop_config/__init__.py
ani2xcur/manager/desktop_config/base.py
ani2xcur/manager/desktop_config/cinnamon.py
ani2xcur/manager/desktop_config/gnome.py
ani2xcur/manager/desktop_config/gtk.py
ani2xcur/manager/desktop_config/kde.py
ani2xcur/manager/desktop_config/lxqt.py
ani2xcur/manager/desktop_config/mate.py
ani2xcur/manager/desktop_config/windows.py
ani2xcur/manager/desktop_config/x_org.py
ani2xcur/manager/desktop_config/xdg.py
ani2xcur/manager/desktop_config/xfce.py
ani2xcur/manager/desktop_config/xsettings.py
ani2xcur/source/bottom_left_corner
ani2xcur/source/bottom_right_corner
ani2xcur/source/bottom_side
ani2xcur/source/center_ptr
ani2xcur/source/circle
ani2xcur/source/cross
ani2xcur/source/dotbox
ani2xcur/source/hand2
ani2xcur/source/left_ptr
ani2xcur/source/left_ptr_watch
ani2xcur/source/left_side
ani2xcur/source/move
ani2xcur/source/pencil
ani2xcur/source/question_arrow
ani2xcur/source/right_ptr
ani2xcur/source/vertical-text
ani2xcur/source/wait
ani2xcur/source/wayland-cursor
ani2xcur/source/xterm
ani2xcur-0.0.7.dist-info/licenses/LICENSE
ani2xcur-0.0.7.dist-info/METADATA
ani2xcur-0.0.7.dist-info/WHEEL
ani2xcur-0.0.7.dist-info/entry_points.txt
ani2xcur-0.0.7.dist-info/top_level.txt
ani2xcur-0.0.7.dist-info/RECORD
