Metadata-Version: 2.4
Name: ani2xcur
Version: 0.0.7
Summary: 一个功能强大的命令行工具，用于在 Windows 和 Linux 平台上发现、转换、安装和管理鼠标指针主题。它支持双向转换，可将 Linux 光标主题 (XCursor) 转为 Windows 格式 (.cur/.ani)，亦可将 Windows 主题转为 Linux 格式，并提供安装、应用和卸载鼠标主题的全套管理功能。
Author: licyk
Classifier: Development Status :: 3 - Alpha
Classifier: Environment :: Win32 (MS Windows)
Classifier: Environment :: X11 Applications
Classifier: Intended Audience :: End Users/Desktop
Classifier: Operating System :: Microsoft :: Windows
Classifier: Operating System :: POSIX :: Linux
Classifier: Programming Language :: Python
Classifier: Programming Language :: Python :: 3 :: Only
Classifier: Programming Language :: Python :: 3.10
Classifier: Programming Language :: Python :: 3.11
Classifier: Programming Language :: Python :: 3.12
Classifier: Programming Language :: Python :: 3.13
Classifier: Programming Language :: Python :: 3.14
Classifier: Topic :: Desktop Environment
Requires-Python: >=3.10
License-File: LICENSE
Requires-Dist: win2xcur>=0.2.0
Requires-Dist: typer
Requires-Dist: click
Requires-Dist: zstandard
Requires-Dist: py7zr
Requires-Dist: rarfile
Requires-Dist: requests
Requires-Dist: tqdm
Requires-Dist: rich
Dynamic: license-file
